{
	"url": "http://www.walmart.com/Value-of-the-Day/prodp",
	"type": "home",
	"tests": [
		{
			"day": "2015-07-25",
			"test": "150724_W8_384ed3955e45a6fd8d84d61d4eca30cb",
			"run": 3,
			"browser": "Google Chrome",
			"browser_version": "44.0.2403.107",
			"byte": 464,
			"render": 2288,
			"dom": 8387,
			"loaded": 8583,
			"size": 1433114,
			"requests": 88,
			"pagespeed": 94,
			"speedindex": 2602
		},
		{
			"day": "2015-07-25",
			"test": "150724_W8_fe1d3e7387a4ed72d6ba899035776171",
			"run": 2,
			"browser": "Google Chrome",
			"browser_version": "44.0.2403.89",
			"byte": 507,
			"render": 2687,
			"dom": 8416,
			"loaded": 14483,
			"size": 1446373,
			"requests": 133,
			"pagespeed": 94,
			"speedindex": 3069
		},
		{
			"day": "2015-07-24",
			"test": "150723_PF_d650ddf20513d0d14864359233975a9c",
			"run": 3,
			"browser": "Google Chrome",
			"browser_version": "44.0.2403.89",
			"byte": 545,
			"render": 2287,
			"dom": 8197,
			"loaded": 8226,
			"size": 1401660,
			"requests": 97,
			"pagespeed": 94,
			"speedindex": 2764
		},
		{
			"day": "2015-07-24",
			"test": "150723_PF_5b2774a5e0252e985e0961291d04cb13",
			"run": 1,
			"browser": "Google Chrome",
			"browser_version": "44.0.2403.89",
			"byte": 474,
			"render": 1885,
			"dom": 9931,
			"loaded": 9931,
			"size": 1497998,
			"requests": 103,
			"pagespeed": 94,
			"speedindex": 2260
		},
		{
			"day": "2015-07-23",
			"test": "150722_FC_bd81426eed868b6989e9a19e85db07e0",
			"run": 1,
			"browser": "Google Chrome",
			"browser_version": "44.0.2403.89",
			"byte": 503,
			"render": 2285,
			"dom": 6513,
			"loaded": 15807,
			"size": 1332863,
			"requests": 141,
			"pagespeed": 91,
			"speedindex": 2657
		},
		{
			"day": "2015-07-23",
			"test": "150722_FC_4119a15b2fbf077b1867046fc7b98315",
			"run": 2,
			"browser": "Google Chrome",
			"browser_version": "44.0.2403.89",
			"byte": 577,
			"render": 1998,
			"dom": 8231,
			"loaded": 8552,
			"size": 1415797,
			"requests": 99,
			"pagespeed": 92,
			"speedindex": 2332
		},
		{
			"day": "2015-07-22",
			"test": "150721_JX_5c669ae6c914c5d96188084930a4716a",
			"run": 1,
			"browser": "Google Chrome",
			"browser_version": "43.0.2357.134",
			"byte": 921,
			"render": 2589,
			"dom": 8390,
			"loaded": 8638,
			"size": 1466903,
			"requests": 94,
			"pagespeed": 92,
			"speedindex": 2966
		},
		{
			"day": "2015-07-22",
			"test": "150721_JX_e461f6fc47501475b96f98f4f0ebc821",
			"run": 2,
			"browser": "Google Chrome",
			"browser_version": "43.0.2357.134",
			"byte": 691,
			"render": 1987,
			"dom": 7897,
			"loaded": 7910,
			"size": 1436289,
			"requests": 99,
			"pagespeed": 92,
			"speedindex": 2516
		},
		{
			"day": "2015-07-21",
			"test": "150720_N7_27271c502b1874347db567d10b125b00",
			"run": 3,
			"browser": "Google Chrome",
			"browser_version": "43.0.2357.134",
			"byte": 407,
			"render": 1889,
			"dom": 7572,
			"loaded": 7879,
			"size": 1414623,
			"requests": 93,
			"pagespeed": 92,
			"speedindex": 2233
		},
		{
			"day": "2015-07-21",
			"test": "150720_8D_3b37a27c36dc71a539de32cd438c6e37",
			"run": 1,
			"browser": "Google Chrome",
			"browser_version": "43.0.2357.134",
			"byte": 743,
			"render": 2188,
			"dom": 8925,
			"loaded": 8925,
			"size": 1507565,
			"requests": 102,
			"pagespeed": 94,
			"speedindex": 3375
		},
		{
			"day": "2015-07-20",
			"test": "150719_9Q_34dbb98ff5ff405e87352359575b1629",
			"run": 2,
			"browser": "Google Chrome",
			"browser_version": "43.0.2357.134",
			"byte": 714,
			"render": 1990,
			"dom": 6693,
			"loaded": 6915,
			"size": 1396356,
			"requests": 90,
			"pagespeed": 92,
			"speedindex": 2839
		},
		{
			"day": "2015-07-20",
			"test": "150719_4M_89f09e29f28c10d83d5bc5890ef0ac7f",
			"run": 2,
			"browser": "Google Chrome",
			"browser_version": "43.0.2357.134",
			"byte": 530,
			"render": 2287,
			"dom": 8440,
			"loaded": 8810,
			"size": 1493089,
			"requests": 92,
			"pagespeed": 92,
			"speedindex": 2425
		},
		{
			"day": "2015-07-19",
			"test": "150718_BJ_6ac65e895500f9c88a3be57eb078961f",
			"run": 3,
			"browser": "Google Chrome",
			"browser_version": "43.0.2357.134",
			"byte": 952,
			"render": 2087,
			"dom": 8362,
			"loaded": 8578,
			"size": 1372061,
			"requests": 96,
			"pagespeed": 92,
			"speedindex": 2763
		},
		{
			"day": "2015-07-19",
			"test": "150718_BJ_2e8e85d818f47d284670598dcf352350",
			"run": 1,
			"browser": "Google Chrome",
			"browser_version": "43.0.2357.134",
			"byte": 744,
			"render": 2188,
			"dom": 8915,
			"loaded": 8972,
			"size": 1448915,
			"requests": 99,
			"pagespeed": 92,
			"speedindex": 2981
		},
		{
			"day": "2015-07-18",
			"test": "150717_H2_31f9d6be922b1041b98ac83494b4d185",
			"run": 3,
			"browser": "Google Chrome",
			"browser_version": "43.0.2357.134",
			"byte": 385,
			"render": 1688,
			"dom": 6358,
			"loaded": 6588,
			"size": 1269203,
			"requests": 79,
			"pagespeed": 92,
			"speedindex": 1985
		},
		{
			"day": "2015-07-18",
			"test": "150717_H2_c7097ff88765c3daedcaa1c42768593d",
			"run": 2,
			"browser": "Google Chrome",
			"browser_version": "43.0.2357.134",
			"byte": 484,
			"render": 1790,
			"dom": 7671,
			"loaded": 7671,
			"size": 1370216,
			"requests": 90,
			"pagespeed": 92,
			"speedindex": 1991
		},
		{
			"day": "2015-07-17",
			"test": "150716_RZ_506a11c4718396d3c8107d57664ad047",
			"run": 2,
			"browser": "Google Chrome",
			"browser_version": "43.0.2357.134",
			"byte": 495,
			"render": 1790,
			"dom": 5776,
			"loaded": 15459,
			"size": 1442374,
			"requests": 135,
			"pagespeed": 92,
			"speedindex": 2065
		},
		{
			"day": "2015-07-17",
			"test": "150716_X6_bfe08ee45eb8d249dcf567d03ae97672",
			"run": 2,
			"browser": "Google Chrome",
			"browser_version": "43.0.2357.134",
			"byte": 1005,
			"render": 3293,
			"dom": 7667,
			"loaded": 8029,
			"size": 1330045,
			"requests": 80,
			"pagespeed": 92,
			"speedindex": 3543
		},
		{
			"day": "2015-07-16",
			"test": "150715_WB_104C",
			"run": 1,
			"browser": "Google Chrome",
			"browser_version": "43.0.2357.134",
			"byte": 271,
			"render": 0,
			"dom": 0,
			"loaded": 408,
			"size": 6107,
			"requests": 1,
			"pagespeed": 94,
			"speedindex": 0
		},
		{
			"day": "2015-07-16",
			"test": "150715_1Y_1049",
			"run": 1,
			"browser": "Google Chrome",
			"browser_version": "43.0.2357.134",
			"byte": 212,
			"render": 0,
			"dom": 0,
			"loaded": 218,
			"size": 6311,
			"requests": 1,
			"pagespeed": 94,
			"speedindex": 0
		}
	]
}